<Ui xmlns="http://www.blizzard.com/wow/ui/" xmlns:xsi="http://www.w3.org/2001/XMLSchema-instance" xmlns:xsd="http://www.w3.org/2001/XMLSchema">
  <Script file="magenuggets_fire.lua"></Script>

  <Frame name="MageNugIgnite_Frame" parent="UIParent" frameStrata="LOW" hidden="true" enableMouse="true" movable="true">
    <Size x="36" y="36"/>
    <Anchors>
      <Anchor point="CENTER"/>
    </Anchors>
    <Layers>
      <Layer level="BACKGROUND">
        <Texture name="$parentIconTexture" file="Interface\Icons\spell_fire_fireball">
          <Size>
            <AbsDimension x="35" y="35"/>
          </Size>
          <Anchors>
            <Anchor point="CENTER" relativePoint="CENTER"/>
          </Anchors>
          <TexCoords left="0" right="1" top="0" bottom="1"/>
        </Texture>
        <Texture name="$parentCombustionTexture" file="Interface\Icons\spell_fire_sealoffire">
          <Size>
            <AbsDimension x="28" y="28"/>
          </Size>
          <Anchors>
            <Anchor point="CENTER" relativePoint="CENTER">
              <Offset>
                <AbsDimension x="-40" y="0"/>
              </Offset>
            </Anchor>
          </Anchors>
          <TexCoords left="0" right="1" top="0" bottom="1"/>
        </Texture>
        <Texture name="$parentPhenonixFlamesTexture" file="Interface\Icons\artifactability_firemage_phoenixbolt">
          <Size>
            <AbsDimension x="28" y="28"/>
          </Size>
          <Anchors>
            <Anchor point="CENTER" relativePoint="CENTER">
              <Offset>
                <AbsDimension x="40" y="0"/>
              </Offset>
            </Anchor>
          </Anchors>
          <TexCoords left="0" right="1" top="0" bottom="1"/>
        </Texture>
      </Layer>
      <Layer level="OVERLAY">
        <Texture name="$parentTexture" file="Interface\UNITPOWERBARALT\Generic1Player_Circular_Frame">
          <Size>
            <AbsDimension x="74" y="74"/>
          </Size>
          <Anchors>
            <Anchor point="CENTER" relativePoint="CENTER">
              <Offset>
                <AbsDimension x="0" y="0"/>
              </Offset>
            </Anchor>
          </Anchors>
          <TexCoords left="0" right="1" top="0" bottom="1"/>
        </Texture>
        <Texture name="$parentTexture2" file="Interface\UNITPOWERBARALT\Generic1Player_Circular_Frame">
          <Size>
            <AbsDimension x="60" y="60"/>
          </Size>
          <Anchors>
            <Anchor point="CENTER" relativePoint="CENTER">
              <Offset>
                <AbsDimension x="-40" y="0"/>
              </Offset>
            </Anchor>
          </Anchors>
          <TexCoords left="0" right="1" top="0" bottom="1"/>
        </Texture>
        <Texture name="$parentTexture3" file="Interface\UNITPOWERBARALT\Generic1Player_Circular_Frame">
          <Size>
            <AbsDimension x="60" y="60"/>
          </Size>
          <Anchors>
            <Anchor point="CENTER" relativePoint="CENTER">
              <Offset>
                <AbsDimension x="40" y="0"/>
              </Offset>
            </Anchor>
          </Anchors>
          <TexCoords left="0" right="1" top="0" bottom="1"/>
        </Texture>
      </Layer>
    </Layers>
    <Frames></Frames>
    <Scripts>
      <OnLoad>
        self:RegisterForDrag("LeftButton"); self.TimeSinceLastUpdate = 0
      </OnLoad>
      <OnDragStart>
        MNLockFrames(self);</OnDragStart>
      <OnDragStop>
        self:StopMovingOrSizing(); self.isMoving = false; MageNuggets_Frames.ignite_point, _, MageNuggets_Frames.ignite_relativePoint, MageNuggets_Frames.ignite_xOfs, MageNuggets_Frames.ignite_yOfs = MageNugIgnite_Frame:GetPoint();
      </OnDragStop>
      <OnEnter>
        Monitors_OnEnter()
      </OnEnter>
      <OnLeave>
        GameTooltip:Hide()
      </OnLeave>
      <OnUpdate>
        MageNuggetsFireblast_OnUpdate(self, elapsed);
      </OnUpdate>
    </Scripts>
  </Frame>

  <Frame name="MageNugIgnite_TextFrame" parent="MageNugIgnite_Frame" frameStrata="MEDIUM" hidden="false" enableMouse="false" movable="true">
    <Size x="36" y="36"/>
    <Anchors>
      <Anchor point="CENTER"/>
    </Anchors>
    <Layers>
      <Layer level="OVERLAY">
        <Texture name="$parentTexture">
          <Size>
            <AbsDimension x="64" y="64"/>
          </Size>
          <Anchors>
            <Anchor point="CENTER" relativePoint="CENTER"/>
          </Anchors>

        </Texture>
      </Layer>
      <Layer level="ARTWORK">
        <FontString name="$parentFlameBlastText" font="Fonts\FRIZQT__.ttf" outline="THICK" inherits="GameFontNormal">
          <Anchors>
            <Anchor point="CENTER">
              <Offset>
                <AbsDimension x="2" y="2"/>
              </Offset>
            </Anchor>
          </Anchors>
          <FontHeight>
            <AbsValue val="18"/>
          </FontHeight>
          <Color r="1" g="1" b="1"/>
        </FontString>
        <FontString name="$parentFlameBlastText2" font="Fonts\FRIZQT__.TTF" outline="THICK" inherits="GameFontNormal">
          <Anchors>
            <Anchor point="left">
              <Offset>
                <AbsDimension x="10" y="-11"/>
              </Offset>
            </Anchor>
          </Anchors>
          <FontHeight>
            <AbsValue val="8"/>
          </FontHeight>
          <color r="1" g="1" b="1"/>
        </FontString>

        <FontString name="$parentPheonixFlamesText" font="Fonts\FRIZQT__.ttf" outline="THICK" inherits="GameFontNormal">
          <Anchors>
            <Anchor point="CENTER">
              <Offset>
                <AbsDimension x="41" y="3"/>
              </Offset>
            </Anchor>
          </Anchors>
          <FontHeight>
            <AbsValue val="12"/>
          </FontHeight>
          <Color r="1" g="1" b="1"/>
        </FontString>
        <FontString name="$parentPheonixFlamesText2" font="Fonts\FRIZQT__.TTF" outline="THICK" inherits="GameFontNormal">
          <Anchors>
            <Anchor point="CENTER">
              <Offset>
                <AbsDimension x="40" y="-8"/>
              </Offset>
            </Anchor>
          </Anchors>
          <FontHeight>
            <AbsValue val="8"/>
          </FontHeight>
          <color r="1" g="1" b="1"/>
        </FontString>
        <FontString name="$parentCombustionText" font="Fonts\FRIZQT__.TTF" outline="THICK" inherits="GameFontNormal">
          <Anchors>
            <Anchor point="CENTER">
              <Offset>
                <AbsDimension x="-39" y="-2"/>
              </Offset>
            </Anchor>
          </Anchors>
          <FontHeight>
            <AbsValue val="8"/>
          </FontHeight>
          <color r="1" g="1" b="1"/>
        </FontString>
      </Layer>
    </Layers>
  </Frame>

  <Frame name="MageNugProcHUFrame" parent="UIParent" hidden="true" enableMouse="true" movable="true">
    <Size x="150" y="30"/>
    <Anchors>
      <Anchor point="CENTER"/>
    </Anchors>
    <Layers>
      <Layer level="OVERLAY">
        <Texture name="$parentTextureBorder" file="Interface\UNITPOWERBARALT\Fire_Horizontal_Frame">
          <Size>
            <AbsDimension x="205" y="65"/>
          </Size>
          <Anchors>
            <Anchor point="CENTER">
              <Offset>
                <AbsDimension x="0" y="0"/>
              </Offset>
            </Anchor>
          </Anchors>
        </Texture>
      </Layer>
      <Layer level="ARTWORK">
        <Texture name="$parentTexture" file="Interface\Icons\ability_Mage_HotStreak">
          <Size>
            <AbsDimension x="26" y="26"/>
          </Size>
          <Anchors>
            <Anchor point="LEFT">
              <Offset>
                <AbsDimension x="2" y="0"/>
              </Offset>
            </Anchor>
          </Anchors>
        </Texture>
        <FontString name="$parentText" font="Fonts\FRIZQT__.TTF" inherits="GameFontNormal">
          <Anchors>
            <Anchor point="CENTER">
              <Offset>
                <AbsDimension x="10" y="3"/>
              </Offset>
            </Anchor>
          </Anchors>
          <FontHeight>
            <AbsValue val="13"/>
          </FontHeight>
        </FontString>
        <FontString name="$parentText2" font="Fonts\FRIZQT__.TTF" inherits="GameFontNormal">
          <Anchors>
            <Anchor point="BOTTOMRIGHT">
              <Offset>
                <AbsDimension x="-3" y="4"/>
              </Offset>
            </Anchor>
          </Anchors>
          <FontHeight>
            <AbsValue val="6"/>
          </FontHeight>
          <color r="1" g="1" b="1"/>
        </FontString>
      </Layer>
    </Layers>
    <Frames>
      <StatusBar name="$parent_ProcBar" inherits="TextStatusBar">
        <Size x="120" y="8"/>
        <Anchors>
          <Anchor point="BOTTOMLEFT" relativeTo="$parent">
            <Offset>
              <AbsDimension x="27" y="2"/>
            </Offset>
          </Anchor>
        </Anchors>
        <BarTexture file="Interface\TargetingFrame\UI-StatusBar"/>
        <Layers>
          <Layer level="OVERLAY">
            <Texture name="$parentSpark" file="Interface\CastingBar\UI-CastingBar-Spark" alphaMode="ADD">
              <Size>
                <AbsDimension x="20" y="20"/>
              </Size>
              <Anchors>
                <Anchor point="BOTTOMLEFT"/>
              </Anchors>
            </Texture>
          </Layer>
        </Layers>
        <Scripts>
          <OnLoad>
            self:SetStatusBarColor(1, 0, 0) self:SetMinMaxValues(0,8)
          </OnLoad>
        </Scripts>
      </StatusBar>
    </Frames>
    <Scripts>
      <OnLoad>
        self:RegisterForDrag("LeftButton"); self.TimeSinceLastUpdate = 0
      </OnLoad>
      <OnDragStart>
        MNLockFrames(self);</OnDragStart>
      <OnDragStop>
        self:StopMovingOrSizing(); self.isMoving = false; MageNuggets_Frames.hu_point, _, MageNuggets_Frames.hu_relativePoint, MageNuggets_Frames.hu_xOfs, MageNuggets_Frames.hu_yOfs = MageNugProcHUFrame:GetPoint();
      </OnDragStop>
      <OnEnter>
        Monitors_OnEnter()
      </OnEnter>
      <OnLeave>
        GameTooltip:Hide()
      </OnLeave>
      <OnUpdate>
        MageNuggetsHU_OnUpdate(self, elapsed)
      </OnUpdate>
    </Scripts>
  </Frame>

  <Frame name="MageNugProcFrame" parent="UIParent" hidden="true" enableMouse="true" movable="true">
    <Size x="150" y="30"/>
    <Anchors>
      <Anchor point="CENTER"/>
    </Anchors>
    <Layers>
      <Layer level="OVERLAY">
        <Texture name="$parentTextureBorder" file="Interface\UNITPOWERBARALT\Fire_Horizontal_Frame">
          <Size>
            <AbsDimension x="205" y="65"/>
          </Size>
          <Anchors>
            <Anchor point="CENTER">
              <Offset>
                <AbsDimension x="0" y="0"/>
              </Offset>
            </Anchor>
          </Anchors>
        </Texture>
      </Layer>
      <Layer level="ARTWORK">
        <Texture name="$parentTexture" file="Interface\Icons\ability_ironmaidens_grapeshotblast">
          <Size>
            <AbsDimension x="26" y="26"/>
          </Size>
          <Anchors>
            <Anchor point="LEFT">
              <Offset>
                <AbsDimension x="2" y="0"/>
              </Offset>
            </Anchor>
          </Anchors>
        </Texture>
        <FontString name="$parentText" font="Fonts\FRIZQT__.TTF" inherits="GameFontNormal">
          <Anchors>
            <Anchor point="CENTER">
              <Offset>
                <AbsDimension x="10" y="3"/>
              </Offset>
            </Anchor>
          </Anchors>
          <FontHeight>
            <AbsValue val="13"/>
          </FontHeight>
        </FontString>
        <FontString name="$parentText2" font="Fonts\FRIZQT__.TTF" inherits="GameFontNormal">
          <Anchors>
            <Anchor point="BOTTOMRIGHT">
              <Offset>
                <AbsDimension x="-3" y="4"/>
              </Offset>
            </Anchor>
          </Anchors>
          <FontHeight>
            <AbsValue val="6"/>
          </FontHeight>
          <color r="1" g="1" b="1"/>
        </FontString>
      </Layer>
    </Layers>
    <Frames>
      <StatusBar name="$parent_ProcBar" inherits="TextStatusBar">
        <Size x="120" y="8"/>
        <Anchors>
          <Anchor point="BOTTOMLEFT" relativeTo="$parent">
            <Offset>
              <AbsDimension x="27" y="2"/>
            </Offset>
          </Anchor>
        </Anchors>
        <BarTexture file="Interface\TargetingFrame\UI-StatusBar"/>
        <Layers>
          <Layer level="OVERLAY">
            <Texture name="$parentSpark" file="Interface\CastingBar\UI-CastingBar-Spark" alphaMode="ADD">
              <Size>
                <AbsDimension x="20" y="20"/>
              </Size>
              <Anchors>
                <Anchor point="BOTTOMLEFT"/>
              </Anchors>
            </Texture>
          </Layer>
        </Layers>
        <Scripts>
          <OnLoad>
            self:SetStatusBarColor(1, 0, 0) self:SetMinMaxValues(0,14)
          </OnLoad>
        </Scripts>
      </StatusBar>
    </Frames>
    <Scripts>
      <OnLoad>
        self:RegisterForDrag("LeftButton"); self.TimeSinceLastUpdate = 0
      </OnLoad>
      <OnDragStart>
        MNLockFrames(self);</OnDragStart>
      <OnDragStop>
        self:StopMovingOrSizing(); self.isMoving = false; MageNuggets_Frames.hs_point, _, MageNuggets_Frames.hs_relativePoint, MageNuggets_Frames.hs_xOfs, MageNuggets_Frames.hs_yOfs = MageNugProcFrame:GetPoint();
      </OnDragStop>
      <OnEnter>
        Monitors_OnEnter()
      </OnEnter>
      <OnLeave>
        GameTooltip:Hide()
      </OnLeave>
      <OnUpdate>
        MageNuggetsHS_OnUpdate(self, elapsed)
      </OnUpdate>
    </Scripts>
  </Frame>

  <Frame name="MageNugPyroclasmProcFrame" parent="UIParent" hidden="true" enableMouse="true" movable="true">
    <Size x="150" y="30"/>
    <Anchors>
      <Anchor point="CENTER"/>
    </Anchors>
    <Layers>
      <Layer level="OVERLAY">
        <Texture name="$parentTextureBorder" file="Interface\UNITPOWERBARALT\Fire_Horizontal_Frame">
          <Size>
            <AbsDimension x="205" y="65"/>
          </Size>
          <Anchors>
            <Anchor point="CENTER">
              <Offset>
                <AbsDimension x="0" y="0"/>
              </Offset>
            </Anchor>
          </Anchors>
        </Texture>
      </Layer>
      <Layer level="ARTWORK">
        <Texture name="$parentTexture" file="Interface\Icons\spell_shaman_lavasurge">
          <Size>
            <AbsDimension x="26" y="26"/>
          </Size>
          <Anchors>
            <Anchor point="LEFT">
              <Offset>
                <AbsDimension x="2" y="0"/>
              </Offset>
            </Anchor>
          </Anchors>
        </Texture>
        <FontString name="$parentText" font="Fonts\FRIZQT__.TTF" inherits="GameFontNormal">
          <Anchors>
            <Anchor point="CENTER">
              <Offset>
                <AbsDimension x="10" y="3"/>
              </Offset>
            </Anchor>
          </Anchors>
          <FontHeight>
            <AbsValue val="13"/>
          </FontHeight>
        </FontString>
        <FontString name="$parentText2" font="Fonts\FRIZQT__.TTF" inherits="GameFontNormal">
          <Anchors>
            <Anchor point="BOTTOMRIGHT">
              <Offset>
                <AbsDimension x="-3" y="4"/>
              </Offset>
            </Anchor>
          </Anchors>
          <FontHeight>
            <AbsValue val="6"/>
          </FontHeight>
          <color r="1" g="1" b="1"/>
        </FontString>
        <FontString name="$parent_CountText" font="Fonts\FRIZQT__.TTF" inherits="GameFontNormal" text="2">
          <Anchors>
            <Anchor point="LEFT">
              <Offset>
                <AbsDimension x="9" y="-2"/>
              </Offset>
            </Anchor>
          </Anchors>
          <FontHeight>
            <AbsValue val="22"/>
          </FontHeight>
          <color r="1" g="1" b="1"/>
        </FontString>
      </Layer>
    </Layers>
    <Frames>
      <StatusBar name="$parent_ProcBar" inherits="TextStatusBar">
        <Size x="120" y="8"/>
        <Anchors>
          <Anchor point="BOTTOMLEFT" relativeTo="$parent">
            <Offset>
              <AbsDimension x="27" y="2"/>
            </Offset>
          </Anchor>
        </Anchors>
        <BarTexture file="Interface\TargetingFrame\UI-StatusBar"/>
        <Layers>
          <Layer level="OVERLAY">
            <Texture name="$parentSpark" file="Interface\CastingBar\UI-CastingBar-Spark" alphaMode="ADD">
              <Size>
                <AbsDimension x="20" y="20"/>
              </Size>
              <Anchors>
                <Anchor point="BOTTOMLEFT"/>
              </Anchors>
            </Texture>
          </Layer>
        </Layers>
        <Scripts>
          <OnLoad>
            self:SetStatusBarColor(1, 0, 0) self:SetMinMaxValues(0,14)
          </OnLoad>
        </Scripts>
      </StatusBar>
    </Frames>
    <Scripts>
      <OnLoad>
        self:RegisterForDrag("LeftButton"); self.TimeSinceLastUpdate = 0
      </OnLoad>
      <OnDragStart>
        MNLockFrames(self);</OnDragStart>
      <OnDragStop>
        self:StopMovingOrSizing(); self.isMoving = false; MageNuggets_Frames.pyroclasm_point, _, MageNuggets_Frames.pyroclasm_relativePoint, MageNuggets_Frames.pyroclasm_xOfs, MageNuggets_Frames.pyroclasm_yOfs = MageNugPyroclasmProcFrame:GetPoint();
      </OnDragStop>
      <OnEnter>
        Monitors_OnEnter()
      </OnEnter>
      <OnLeave>
        GameTooltip:Hide()
      </OnLeave>
      <OnUpdate>
        MageNuggetsPyroclasm_OnUpdate(self, elapsed)
      </OnUpdate>
    </Scripts>
  </Frame>

</Ui>
